README.md
setup.py
north_utils/__init__.py
north_utils/__version__.py
north_utils/buffer.py
north_utils/crc.py
north_utils/dict.py
north_utils/encoding.py
north_utils/errors.py
north_utils/joystick.py
north_utils/location.py
north_utils/mixins.py
north_utils/motion.py
north_utils/package.py
north_utils/process.py
north_utils/registry.py
north_utils/test.py
north_utils.egg-info/PKG-INFO
north_utils.egg-info/SOURCES.txt
north_utils.egg-info/dependency_links.txt
north_utils.egg-info/requires.txt
north_utils.egg-info/top_level.txt