Metadata-Version: 2.1
Name: north-utils
Version: 0.0.15
Summary: Utilities shared across North packages
Home-page: https://gitlab.com/north-robotics/north_utils
Author: Sean Clark
Author-email: sean@v13inc.com
License: MIT
Platform: UNKNOWN
Requires-Python: >=3.6.0
